{"marca":"Renault","precio":444,"patente":"aaa115","path":"fotos/aaa115.jpg"}
{"marca":"BMW","precio":1234,"patente":"aaa114","path":"fotos/aaa114.jpg"}
{"marca":"BMW","precio":123,"patente":"aaa111","path":"fotos/aaa111.jpg"}
{"marca":"Renault","precio":123,"patente":"aaa456","path":"fotos/aaa456.jpg"}
{"marca":"Honda","precio":15423,"patente":"aaa112","path":"fotos/aaa112.jpg"}
{"marca":"Renault","precio":5656,"patente":"aaa","path":"fotos/aaa.jpg"}
{"marca":"Renault","precio":5464,"patente":"asd","path":"fotos/asd.jpg"}
{"marca":"Renault","precio":245,"patente":"aaaaa","path":"fotos/aaaaa.jpg"}
{"marca":"Renault","precio":0,"patente":"456","path":"fotos/456.jpg"}